[{"name": "Vendi le tue cose", "image": "https://raw.githubusercontent.com/E-Money-Online/E-Money-Data/main/images/pro_1.png", "description": "Come vendere velocemente oggetti in cambio di contanti\n\nPrima di entrare nell'elenco, \u00e8 importante capire quali sono le opzioni a tua disposizione quando si tratta di scaricare gli oggetti indesiderati.\n\nEsistono alcuni modi in cui puoi vendere cose:\n\nVendere direttamente a un'azienda Ok, con alcune aziende fai sapere loro quali articoli hai in vendita e poi ti faranno un preventivo.\n\nSe ti piace il preventivo offerto, dovrai spedire la tua roba all'azienda.\n\nOra, molte di queste aziende ti forniranno un'etichetta di spedizione prepagata, quindi inviare loro i tuoi articoli \u00e8 totalmente gratuito!\n\nUna volta che l'azienda riceve il tuo articolo, verrai pagato.\n\nQuesto \u00e8 un modo semplice e veloce per vendere oggetti usati.\n\nInoltre, ci sono negozi fisici dove puoi portare le tue cose e ottenere rapidamente contanti per i tuoi articoli.\n\nPuoi vendere le tue cose:\n\n1) eBay\n2)Amazzonia\n3) Craigslist\n4) Flipkart\n5) Marchio elegante\n6) Vinificato\n7) Tradesy\n8) Riconfezionare\n9) Leprix\n10) Tregua"}, {"name": "Diventa un affiliato di marketing", "image": "https://raw.githubusercontent.com/E-Money-Online/E-Money-Data/main/images/pro_2.png", "description": "Il marketing di affiliazione sta rapidamente diventando uno dei modi pi\u00f9 efficaci per fare soldi online. Non \u00e8 uno schema per arricchirsi; ci vuole tempo e pazienza per costruire relazioni con le aziende che stai commercializzando e con i consumatori che raggiungi con i tuoi contenuti. Detto questo, molte persone sono interessate a imparare come diventare un affiliato di marketing grazie alla libert\u00e0 e alle opportunit\u00e0 finanziarie che pu\u00f2 offrire praticamente a chiunque.\n\nCos\u2019\u00e8 il marketing di affiliazione?\n\nIl marketing di affiliazione \u00e8 il processo per guadagnare denaro promuovendo aziende e prodotti che puoi sostenere. Con l'introduzione di Internet, le aziende hanno iniziato a rendersi conto che era la piattaforma perfetta da utilizzare per distribuire i beni e i servizi offerti a un pubblico pi\u00f9 ampio e diversificato. Il settore dell'e-commerce su Internet \u00e8 diventato uno strumento disponibile per qualsiasi individuo o azienda che desideri raggiungere un pubblico pi\u00f9 ampio.\n\nSe vuoi diventare un affiliato di marketing, l'importante \u00e8 creare rapporti con inserzionisti, editori e consumatori. Gli inserzionisti sono le aziende che vendono prodotti e servizi, l'editore aiuta l'azienda a promuovere questi prodotti e i consumatori sono considerati il \u200b\u200bpubblico che sperimenta queste aziende attraverso l'esposizione e la pubblicit\u00e0 online.\n\nCome funziona il marketing di affiliazione?\n\nIl marketing di affiliazione si basa sulla condivisione delle entrate ed \u00e8 un tipo di programma di incentivi. L\u2019obiettivo del marketing \u00e8 costruire un\u2019alleanza con un marchio, prodotto, servizio o azienda e commercializzare questi servizi alle persone online. Il consulente di marketing affiliato condivide una percentuale dei profitti dell'azienda in cambio di affari di valore e visibilit\u00e0 acquisita. Qui vengono applicati gli stessi concetti di pubblicit\u00e0 di marketing utilizzati negli annunci televisivi e sulla stampa, solo che la piattaforma utilizzata per invogliare e attrarre i consumatori \u00e8 su Internet.\n\nLe reti di social media, i cartelloni pubblicitari digitali e i contenuti dei blog sono tutte tecniche pratiche applicate nel marketing. Marketing efficace significa fornire contenuti unici e di valore che distinguano un'azienda dalla concorrenza. Costruire un marchio forte e accrescere l'integrit\u00e0 dell'azienda \u00e8 essenziale per una campagna di marketing di successo. Quando si inizia nel settore del marketing, \u00e8 necessario dare priorit\u00e0 a diversi obiettivi chiave:\n\n1. Per diventare un affiliato di marketing, dovresti considerare fortemente di concentrarti sulle entrate ricorrenti; ci\u00f2 significa che il flusso di reddito pu\u00f2 essere regolarmente prevedibile di mese in mese anzich\u00e9 sporadico e in periodi piccoli e brevi distribuiti su diversi mesi. Le entrate ricorrenti, o reddito residuo, sono denaro guadagnato continuamente mentre nessun lavoro viene attualmente svolto. Tutto il tempo \u00e8 gi\u00e0 stato investito; questo \u00e8 utile quando si cerca di eliminare le congetture quando si tratta di riuscire a mantenere un reddito costante.\n\n2. Non fare mai affidamento su un'unica fonte di traffico. Aspettatevi sempre l'inaspettato quando si tratta di marketing. Non mettere tutte le uova nello stesso paniere, come dice il vecchio proverbio. Padroneggia una fonte e poi passa a quella successiva. Cercare di diventare un affiliato di marketing \u00e8 noioso e probabilmente inizierai con una sola fonte di traffico principale come i motori di ricerca, ma col tempo vorrai diversificare il pi\u00f9 possibile.\n\n3. Non dimenticare gli utenti mobili. Molta attenzione viene posta sui siti Web e sul traffico web, ma negli ultimi anni sempre pi\u00f9 persone hanno utilizzato il proprio telefono come strumento Internet principale. Quando si fa marketing, tutte le tecniche implementate dovrebbero includere anche visualizzazioni ottimizzate per i dispositivi mobili per coloro che utilizzano i propri telefoni, il che significa raggiungere un pubblico pi\u00f9 ampio e ottenere pi\u00f9 traffico e clic, il che a sua volta significa maggiori entrate.\n\n4. Conoscere le tendenze attuali e stagionali e stare al passo con loro; questo \u00e8 importante per poter ottenere prevedibilit\u00e0, soprattutto considerando le varianti del flusso di reddito.\n\n5. Concentrarsi sul targeting per argomento piuttosto che sul targeting per parole chiave. Gli annunci e le parole pubblicitarie dovrebbero essere inseriti su siti con contenuti strettamente correlati al focus del marketing attuale."}, {"name": "Avvia un'attivit\u00e0 Amazon FBA", "image": "https://raw.githubusercontent.com/E-Money-Online/E-Money-Data/main/images/pro_3.png", "description": "Se sei nuovo a questo concetto di business online, FBA sta per Fulfillment by Amazon\u201d. Amazon elencher\u00e0 i tuoi prodotti sul proprio sito Web e quando arriva una vendita, faranno tutto il duro lavoro per prepararlo per l'invio e consegnare il prodotto al cliente. In sostanza stai sfruttando la potente rete di distribuzione e la base clienti di Amazon. Amazon Warehouses, evade i tuoi ordini e fornisce anche il servizio clienti ai tuoi clienti, cos\u00ec non devi farlo tu. Amazon ti consente di agire come una grande azienda, ma senza i grattacapi di esserlo effettivamente. Tutto quello che devi fare \u00e8 trovare Amazon per vendere.\n\nChe cos'\u00e8 un'attivit\u00e0 FBA?\n\nUn'attivit\u00e0 FBA \u00e8 un modello di business con il quale puoi sfruttare la potente rete di distribuzione e la base clienti di Amazon. Probabilmente hai gi\u00e0 stabilito che utilizzando questo modello di business, il magazzino di Amazon, evade i tuoi ordini e fornisce anche il servizio clienti ai tuoi clienti, essenzialmente gli imprenditori, come te, possono agire come una grande azienda, ma senza i grattacapi di in realt\u00e0 essendo uno. Trascorri il tuo tempo alla ricerca di prodotti redditizi e Amazon si occupa del resto per tuo conto.\n\nQuali vantaggi puoi aspettarti da un'attivit\u00e0 FBA?\n\nUn'azienda di e-commerce di solito deve affrontare la logistica per evadere gli ordini e spedire i prodotti ai propri clienti in modo tempestivo. Utilizzando la potenza di Amazon, elimini quella particolare sfida dalla tua equazione operativa. Un'altra complessit\u00e0 di un negozio di e-commerce \u00e8 tenere traccia dell'inventario e elencare i prodotti. Utilizzando il modello di business FBA, spedisci i prodotti al magazzino di Amazon e consenti loro di prendersi cura del resto.\n\nPassaggi per avviare un'attivit\u00e0 FBA e creare un piano aziendale FBA:\n\nPASSO 1: Crea un account venditore Amazon\n\nPASSO 2: Scegli la tua nicchia\n\nFASE 3: Prodotti di ricerca\n\nPASSO 4: Stabilisci l'approvvigionamento del prodotto\n\nPASSO 5: Stabilisci il tuo marchio\n\nPASSO 6: Crea le tue schede di prodotto\n\nPASSO 7: Commercializzare il tuo prodotto"}, {"name": "Avvia un blog e monetizzalo", "image": "https://raw.githubusercontent.com/E-Money-Online/E-Money-Data/main/images/pro_4.png", "description": "Avviare un blog \u00e8 un'idea davvero semplice per una piccola impresa che richiederebbe solo fino a 1 ora del tuo tempo a settimana e circa $ 20 di costi. Nel corso del tempo potrebbe farti guadagnare un bel po' di soldi.\n\n            Siti come Viralnova.com e Fukarf.com creano contenuti avvincenti trovando storie divertenti, emozionanti e stimolanti su Reddit, Facebook e Imgur, riscrivendo il contenuto, aggiungendo qualche dettaglio in pi\u00f9 e pubblicando il contenuto sul proprio sito.\n\n            Giusto per darti un'idea del successo di questi tipi di siti, ViralNova \u00e8 stata fondata da un ragazzo che ha assunto un paio di scrittori per riscrivere contenuti di successo pubblicati su altri siti sul web. Questo sito \u00e8 stato venduto per 100 MILIONI DI DOLLARI!!! Prima di ci\u00f2, ViralNova guadagnava pi\u00f9 di $ 400.000 al mese in entrate pubblicitarie.\n\n            Con un po\u2019 di promozione su siti come Twitter, Facebook, Linkedin, Reddit ed eventualmente traffico organico, entro 12 mesi dovresti ottenere dalle 30.000 alle 50.000 visite uniche al mese. Monetizza il sito con Adsense per ottenere delle entrate per coprire i costi del tuo hosting e dei nomi di dominio.\n\n            Ok, all'inizio guadagnerai noccioline (da $ 10 a $ 50 al mese), ma man mano che il traffico cresce, questa cifra potrebbe aumentare fino a $ 1000 + al mese. Quindi potenzialmente potresti capovolgere il sito per 30 volte le entrate mensili. Conosco persone che lo fanno continuamente e sfogliano i siti dopo 8 mesi per pi\u00f9 di $ 10.000! Ok, all'inizio guadagnerai noccioline (da $ 10 a $ 50 al mese), ma man mano che il traffico cresce, questa cifra potrebbe crescere fino a $ 1000 + un mese. Quindi potenzialmente potresti capovolgere il sito per 30 volte le entrate mensili. Conosco persone che lo fanno continuamente e sfogliano siti dopo 8 mesi per $ 10.000 +!"}, {"name": "Inizia a fare trading su azioni e Forex", "image": "https://raw.githubusercontent.com/E-Money-Online/E-Money-Data/main/images/pro_5.png", "description": "Il trading valutario \u00e8 una delle opzioni di investimento pi\u00f9 redditizie per gli investitori al dettaglio. Ma la mancanza di conoscenze, risorse e leggi governative vaghe hanno scoraggiato gli investitori al dettaglio della classe media dal partecipare ai mercati forex.\n\n            Cos'\u00e8 il trading valutario?\n\n            Il trading valutario, il trading forex e il trading FX sono tutti la stessa cosa e si riferiscono all'acquisto e alla vendita di coppie di valute a scopo di copertura, speculazione o arbitraggio.\n\n            Quali sono le basi del trading valutario?\n\n            Per padroneggiare il trading valutario, devi essere ben informato\n\n            Quali sono le basi del trading valutario?\n\n            Per padroneggiare il trading valutario, devi essere ben informato sulle nozioni di base del trading valutario come:\n\n            Coppie di valute:\n            Le valute sono sempre scambiate in coppia\n\n            Fai offerte e chiedi:\n            Il prezzo al quale viene acquistata una valuta \u00e8 noto come prezzo \"bid\", mentre il prezzo al quale viene venduta una valuta \u00e8 noto come prezzo \"ask\".\n\n            Diffusione:\n            La differenza tra il prezzo bid e quello ask \u00e8 nota come \"spread\".\n\n            Seme:\n            Un punto nel prezzo o pip \u00e8 il pi\u00f9 piccolo movimento (variazione) nei tassi di cambio della coppia di valute\n\n            Molti:\n            A differenza del mercato azionario in cui \u00e8 possibile acquistare 1 azione, il mercato valutario si occupa di lotti.\n\n            Leva:\n            La leva finanziaria ti aiuta ad assumere grandi posizioni a fronte di una piccola garanzia, ovvero il margine."}, {"name": "Crea un negozio di e-commerce", "image": "https://raw.githubusercontent.com/E-Money-Online/E-Money-Data/main/images/pro_6.png", "description": "Costruire un negozio di e-commerce online non deve essere cos\u00ec impegnativo come sembra. Una volta che hai preso le misure per trovare un prodotto da vendere ai tuoi clienti, \u00e8 il momento di mettere insieme i pezzi del tuo negozio per garantire che i consumatori possano trovarlo, navigarlo e acquistarlo con facilit\u00e0.\n\n            Per essere chiari, non devi farlo da solo. Puoi assumere un'agenzia di e-commerce per fare tutto il lavoro per te, il che pu\u00f2 migliorare significativamente i tuoi sforzi e far crescere il tuo negozio pi\u00f9 velocemente\n\n            Di cosa hai bisogno per creare un negozio online?\n\n            Il primo passo \u00e8 comprendere i vari tipi di software che puoi utilizzare per aiutarti a creare un negozio di e-commerce. Non lasciarti sopraffare da questo processo. Questi strumenti sono progettati per essere molto facili da usare e, una volta installati, sono altamente affidabili e facili da apprendere. Non tutto deve essere completamente personalizzato, puoi anche utilizzare i seguenti strumenti per un ulteriore aiuto:\n\n            - Modelli di siti Web e plug-in Shopify\n\n            - Software di email marketing e software di revisione\n\n            - Software per imposte e spedizioni\n\n            Dopo aver investito nel software giusto, ci sono diversi passaggi chiave da eseguire per preparare il tuo negozio di e-commerce. Lavora su questi uno alla volta.\n\n            1. Crea un piano del negozio:\n\n            Sebbene il tuo piano venga creato principalmente durante i passaggi seguenti, tieni presente anche qual \u00e8 il tuo obiettivo per il tuo negozio di e-commerce. Hai il tuo prodotto. Hai un elenco dei vantaggi che offre? Hai elaborato un piano per stabilire a chi rivolgerti come clienti? Hai qualche idea di layout per il tuo negozio? Scrivi tutte le tue idee."}, {"name": "Diventa un consulente di social media", "image": "https://raw.githubusercontent.com/E-Money-Online/E-Money-Data/main/images/pro_7.png", "description": "Allora, vuoi diventare un consulente di social media? \u00c8 un'ottima scelta di carriera!\n\n            I consulenti di social media sono molto richiesti e con il giusto approccio puoi trovare numerosi clienti a cui offrire servizi di social media. \u00c8 un lavoro che puoi svolgere da casa come libero professionista o avviando un'attivit\u00e0 di consulenza sui social media e guadagnare un ottimo stipendio\n\n            In questa guida completa imparerai cosa fa un consulente di social media, quanti soldi puoi guadagnare e i passaggi esatti da seguire per diventare un professionista di successo dei social media.\n\n            Le grandi aziende e le imprese possono facilmente assumere un coordinatore del personale a tempo pieno o un'agenzia corrispondente per gestire i propri account Twitter, Facebook, LinkedIn e Instagram, ma le imprese pi\u00f9 piccole spesso devono gestire il proprio marketing per i social media. Ma, poich\u00e9 hanno un gran numero di altre responsabilit\u00e0, molte volte gli imprenditori sono troppo sopraffatti o occupati per dedicare molto tempo allo sviluppo del loro approccio ai social media.\n\n            Cos'\u00e8 un consulente di social media?\n\n            Un consulente di social media \u00e8 un individuo qualificato che offre servizi di marketing sui social media ai clienti. I servizi includono la pianificazione e l'esecuzione di una strategia di social media per promuovere il marchio, il prodotto e i servizi di un'azienda sui social media.\n\n            Ci\u00f2 che differenzia i consulenti dagli altri social media marketer \u00e8 che per diventare un consulente \u00e8 necessario avere un'ottima conoscenza del social\n\n            settore dei media nel suo complesso e non solo una rete particolare.\n\n            Il ruolo di un consulente di social media \u00e8 quello di esaminare il quadro generale e progettare una strategia completa su come un marchio pu\u00f2 trarre vantaggio dalle reti di social media. Quindi \u00e8 compito degli specialisti di social media marketing e dei social media manager eseguire la strategia stabilita dal consulente\n\n            7 passaggi per diventare un consulente di social media:\n\n            1. Sviluppa le tue capacit\u00e0 di marketing sui social media\n\n            2. Lavora sui tuoi profili sui social media 3. Acquisisci esperienza pratica\n\n            4. Costruisci un portfolio sui social media\n\n            5. Partecipa alla comunit\u00e0 dei social media\n\n            6. Blog su argomenti di social media\n\n            7. Costruisci il tuo team sui social media (facoltativo)\n\n            Quanto guadagnano i consulenti di social media?\n\n            Secondo varie statistiche, le tariffe orarie per la consulenza sui social media variano tra $ 100 e $ 120 l'ora. Questo \u00e8 il tasso dei consulenti affermati. Per i principianti, la tariffa \u00e8 compresa tra $ 20 e $ 50 l'ora e per i livelli intermedi $ 50 - $ 100 l'ora. L'importo che addebiterai per i tuoi servizi dipende dalla tua esperienza, dal paese in cui operi e dall'importo che un cliente \u00e8 disposto a pagare per i servizi di social media."}, {"name": "Libero professionista professionista", "image": "https://raw.githubusercontent.com/E-Money-Online/E-Money-Data/main/images/pro_8.png", "description": "Il freelance via Internet \u00e8 un ottimo modo per gli esperti nelle loro attivit\u00e0 individuali di aiutare una variet\u00e0 di clienti in generale. Diversi siti Web freelance e basati su progetti consentono alle aziende che necessitano di ulteriore aiuto di elencare i propri progetti. Piccole imprese e liberi professionisti offrono proposte, idee o offerte, grazie alle quali gli acquirenti possono facilmente scegliere ci\u00f2 che desiderano e di cui hanno bisogno. Siti come Elance o Upwork coprono praticamente tutto, inclusa la scrittura di contenuti, la creazione di progetti grafici, la programmazione e l'immissione di dati\n\n            Le grandi aziende e le imprese possono facilmente assumere un coordinatore del personale a tempo pieno o un'agenzia corrispondente per gestire i propri account Twitter, Facebook, LinkedIn e Instagram, ma le imprese pi\u00f9 piccole spesso devono gestire il proprio marketing per i social media. Ma, poich\u00e9 hanno un gran numero di altre responsabilit\u00e0, molte volte gli imprenditori sono troppo sopraffatti o occupati per dedicare molto tempo allo sviluppo del loro approccio ai social media.\n\n            Come ottenere lavori freelance?\n\n            Molte applicazioni forniscono lavori freelance. Ad esempio, \"Fiverr\", \"Assumi e trova lavoro per liberi professionisti\", Upwork per liberi professionisti. Queste applicazioni stanno andando alla grande nell'assunzione e nella fornitura di posti di lavoro. Collegare i tuoi social media, ad esempio, anche una pagina Facebook o un profilo aziendale Instagram, aiuta ad attirare clienti. Inizialmente, devi svolgere quanti pi\u00f9 lavori possibile per acquisire esperienza lavorativa e costruire la tua base di clienti. Successivamente, puoi concentrarti sui tuoi clienti principali ed essere selettivo riguardo al tuo lavoro. Essere regolari nel proprio lavoro \u00e8 una grande virt\u00f9, ma nel campo del freelance, attenersi ai clienti che ti danno un lavoro regolare, funziona come una virt\u00f9 di successo.\n\n            Lavorare onestamente quando nessuno ti guarda definisce un grande senso di integrit\u00e0, e viene applicato anche nel campo del freelance. Il freelance \u00e8 un lavoro da casa. Puoi essere onesto o disonesto, e questo \u00e8 ci\u00f2 che influenza in gran parte il tuo lavoro e il tuo futuro. Concentrati sull'ottenere buone recensioni dai tuoi clienti essendo brutalmente onesto riguardo al tuo lavoro, alla tua professione e al tuo capo.\n\n            Dopo aver generato un profilo forte e creato impressioni lavorative efficaci, devi rimanere in contatto con i tuoi clienti e contattarli di tanto in tanto. Sii nei loro buoni libri, in modo che non debbano passare da te a un altro dipendente o freelance per il loro lavoro. Rendi i tuoi clienti cos\u00ec affidabili nel tuo lavoro che il solo pensiero di passare da te a un altro crea in loro un senso di esitazione.\n\n            Il freelance \u00e8 un'ottima piattaforma che offre numerose opportunit\u00e0 di lavoro nel campo desiderato, inseguendo il tuo hobby o passione nel tempo libero per trarne un reddito. Inoltre, ti d\u00e0 l'opportunit\u00e0 di lavorare direttamente con la persona piuttosto che con l'intera azienda. Il tuo cliente \u00e8 la tua unica attivit\u00e0.\n\n            Competenze richieste per diventare un libero professionista\n\n            Nel freelance, le soft skills sono pi\u00f9 importanti delle hard skills. Per optare sono necessarie competenze hard per il lavoro su cui ti stai concentrando, tuttavia, le competenze trasversali continuano a caratterizzare la loro presenza. Poich\u00e9 queste competenze non derivano da alcuna qualifica o anni di frequenza a scuola o all'universit\u00e0, \u00e8 ancora pi\u00f9 importante sapere quali sono le competenze trasversali giuste per trasformarti in un libero professionista.\n\n            Il primo dell'elenco indica capacit\u00e0 di comunicazione efficaci. La comunicazione \u00e8 l'abilit\u00e0 pi\u00f9 importante di cui si ha bisogno in tutti i ceti sociali. Una comunicazione efficace contribuisce a rendere efficiente il tuo lavoro. Sviluppare un modo informativo di scrivere e parlare in modo chiaro e diretto rappresenta due delle competenze pi\u00f9 importanti di questa sezione. Evita di usare abbreviazioni e termini tecnici e concentrati sull'esposizione dei fatti. Parla in modo professionale!\n\n            Il prossimo sulla lista sarebbe lo sviluppo del pensiero critico per le capacit\u00e0 di risoluzione dei problemi. Uno dei modi per svilupparli \u00e8 lavorare su una serie di \"what if\" e analizzare il problema dato da tutti gli aspetti e da ogni punto di vista possibile. Affronta il problema con mente fredda e con un approccio creativo.\n\n            Infine nell'elenco c'\u00e8 la puntualit\u00e0, che ancora una volta \u00e8 un'abilit\u00e0 importante richiesta in tutti gli ambiti della vita. Quando sei puntuale nell'inviare il tuo lavoro impeccabile, guadagni la fiducia dei tuoi clienti e ottieni una buona recensione, che a sua volta pu\u00f2 attirare pi\u00f9 clienti. Quindi diventa molto importante come dipendente rispettare le scadenze e non oltrepassarle.\n\n            Tutti i migliori campioni diventano i migliori freelance l\u00e0 fuori. Mantieni l'integrit\u00e0 nel tuo lavoro e vola in alto."}, {"name": "Diventa un Vlogger Youtuber", "image": "https://raw.githubusercontent.com/E-Money-Online/E-Money-Data/main/images/pro_9.png", "description": "Le persone stanno cambiando il modo in cui cercano e consumano contenuti su Internet. Non si tratta pi\u00f9 solo di articoli ricchi di testo che le persone leggono trovandoli in una ricerca su Google. Gli utenti di Internet sono ora sempre pi\u00f9 coinvolti dai rich media come i video. Poich\u00e9 sono pi\u00f9 coinvolti, i vlogger sono in grado di sfruttare questo aspetto per ottenere un guadagno finanziario. I vlogger possono guadagnare milioni di dollari all'anno dal loro pubblico.\n\n            I video stanno diventando incredibilmente pi\u00f9 popolari, soprattutto tra gli utenti sotto i 25 anni. Ci sono cos\u00ec tante piattaforme di contenuti video efficaci in offerta come Instagram e Snapchat Stories, Facebook Live video e Youtube. Con questi punti vendita hai la possibilit\u00e0 di diffondere i tuoi contenuti a centinaia di milioni di persone in tutto il mondo. Se ti sei sempre immaginato una celebrit\u00e0 di Internet e ti piace l'idea di stare davanti alla telecamera, allora questo \u00e8 il momento di agire.\n\n            Si possono guadagnare cos\u00ec tanti soldi avviando un vlog o un canale Youtube. Puoi potenzialmente guadagnare migliaia di dollari al mese recensendo e promuovendo prodotti per aziende e marchi. Maggiore \u00e8 il traffico che crei sul tuo canale YouTube, maggiori saranno le entrate pubblicitarie che riceverai da YouTube e potenzialmente dalle offerte di marchi di terze parti.\n\n            Sii te stesso. Quando sei te stesso nei tuoi video, inizi a sentirti a tuo agio con te stesso. Il pericolo di non essere te stesso sta distruggendo la fiducia con i tuoi abbonati. Se cerchi di essere qualcun altro nei tuoi video, significa che reciterai davanti alla telecamera ogni giorno. Ci\u00f2 pu\u00f2 diventare stancante e noioso.\n\n            Considera il tuo pubblico. Ti stai rivolgendo ai pi\u00f9 giovani? Persone anziane? Di cosa parlerai nel vlog? Considera queste domande prima di accedere a YouTube.\n\n            Non nascondere le emozioni nei tuoi video. Il vlogging \u00e8 come il tuo diario. Mostri le tue emozioni e dici al tuo pubblico come ti senti. Non andare davanti alla telecamera e comportarti in modo felice quando sai che ti senti male. D\u00ec ai tuoi spettatori come ti senti.\n\n            Circondati di persone positive. Permetti alle persone di entrare nella tua vita solo se sono l\u00ec per motivarti, non per abbatterti. Quando le persone ti criticano continuamente, a volte ci\u00f2 pu\u00f2 influenzare la tua giornata e potenzialmente rovinare il tuo umore. Discuti le cose con la tua famiglia. Vedi se vogliono essere nei tuoi vlog. Fai loro delle domande e vedi se sono d'accordo se li lasci entrare nei vlog.\n\n            Considera la relazione in cui ti trovi. A volte,\n\n            mettere la tua vita su Internet potrebbe non essere sempre adatto al tuo partner. Parlane con il tuo\n\n            partner e vedi se va bene! Ci sono pericoli nel vloggare la tua vita su YouTube quando sei in a\n\n            relazione, perch\u00e9 gli spettatori sono inclini a criticarla indipendentemente dal fatto che lo sappiano o meno. A volte lo far\u00e0\n\n            dubiti della tua relazione. Un altro pericolo \u00e8 non sapere. A volte, avere una relazione con a\n\n            persona mentre si trova davanti alla telecamera pu\u00f2 creare confusione. Voi\n\n            finir\u00f2 per cercare di capire se lo ami davvero\n\n            persona, o se il tuo amore per quella persona \u00e8 solo per quella persona\n\n            telecamera. Considera la tua relazione prima di crearla\n\n            il passo per diventare un vlogger.\n\n            Quando avvii per la prima volta i tuoi vlog, non aspettarti di guadagnare un milione di iscritti in un giorno. Tecnicamente, quando arrivi su YouTube per la prima volta, probabilmente penserai: \"Oh mio Dio, ora diventer\u00f2 famoso!\". Questo non \u00e8 proprio vero. Ci vogliono anni per ottenere cos\u00ec tanti abbonati e, una volta che ti rendi conto che non hai tutti gli abbonati che volevi, ti senti facilmente frustrato. Stabilisci obiettivi realistici per te stesso. Forse in un video, prova a ottenere solo cinque visualizzazioni su quel video. Quindi, nel video successivo, prova a ottenere dieci visualizzazioni. Migliora te stesso e aumenta gradualmente le tue visualizzazioni e i tuoi iscritti.\n\n            Preparazione alla registrazione:\n\n            Prepara la tua attrezzatura. Non \u00e8 necessario acquistare l'attrezzatura o le fotocamere migliori per i tuoi vlog. La cosa principale su cui dovresti concentrarti \u00e8 procurarti una videocamera con una buona qualit\u00e0 HD e una che offra una buona qualit\u00e0 del suono ai tuoi spettatori. Questi possono essere trovati in qualsiasi negozio vicino a te.\n\n            Costruisci il tuo marchio di vlogging:\n\n            Imparare a usare i social media. Quando avvii YouTube, dovrai mantenere il tuo pubblico aggiornato sulla tua vita. Ci\u00f2 significa che dovrai sapere come utilizzare Twitter, Facebook, Snapchat, Instagram, ecc. Se non sai come navigare in nessuno dei siti di social media sopra indicati, cercalo su Google e vedi se riesci a trovare alcune istruzioni dettagliate.\n\n            Impara a modificare i video. Questa \u00e8 una cosa importante che hai\n\n            sapere come usare. Comprendi cosa puoi fare\n\n            fare per migliorare i tuoi video. In quel momento, potresti esserlo\n\n            utilizzando Windows MovieMaker. Va bene. Come dichiarato\n\n            sopra, non avrai davvero bisogno della migliore attrezzatura per vloggare. Alla fine, puoi trovare un software di editing migliore di tua scelta.\n\n            Carica i tuoi video sul tuo lavoro. Quando ti iscrivi a YouTube, non guadagnerai automaticamente soldi. A meno che tu non ne riceva una buona quantit\u00e0\n\n            visualizzazioni dei tuoi video, non abbandonare il tuo lavoro quotidiano\n\n            Ancora.\n\n            Ascolta il tuo pubblico. Chiedi loro suggerimenti e falli sentire parte della tua vita. Se stai cercando suggerimenti per il nome, ad esempio, ragazzi, sto cercando un buon nome per il mio criceto (o qualunque sia il caso). Fammi sapere nei commenti qui sotto cosa ne pensi."}, {"name": "Crea sul corso online", "image": "https://raw.githubusercontent.com/E-Money-Online/E-Money-Data/main/images/pro_10.png", "description": "Al giorno d'oggi, sempre pi\u00f9 persone sono alla ricerca di nuovi tipi di contenuti di qualit\u00e0 da esplorare online, soprattutto quando si tratta di apprendere nuove competenze. Un modo per soddisfare questa crescente domanda, generando allo stesso tempo entrate, \u00e8 creare e vendere un corso online.\n\n            Trasmettere conoscenze e competenze tramite un corso online ti consentir\u00e0 di posizionarti come un'autorit\u00e0 nel tuo campo, promuovere una comunit\u00e0 di persone che la pensano allo stesso modo attorno alla tua attivit\u00e0 ed espandere la tua portata, il tutto da casa tua.\n\n            Questa guida ti guider\u00e0 attraverso i diversi passaggi su come creare un corso online. Dalla scelta dell'argomento giusto alla creazione di un sito web per il tuo corso e al guadagno: ecco tutto ci\u00f2 che devi sapere:\n\n            01. Scegli l'argomento giusto:\n\n            L'argomento che scegli \u00e8 interamente nelle tue mani e pu\u00f2 essere praticamente qualsiasi cosa, dai consigli per cucinare alla progettazione del sito web. Sebbene le possibilit\u00e0 siano pressoch\u00e9 infinite, l'argomento giusto \u00e8 un fattore determinante per il successo di un corso online.\n\n            I criteri principali nel valutare l'argomento del tuo corso online sono se piace sia a te che al tuo pubblico:\n\n            Scegli qualcosa che vuoi insegnare:\n\n            Scegli qualcosa che gli altri vogliono imparare:\n\n            02. Metti alla prova la tua idea:\n\n            La creazione di un corso online richiede molto duro lavoro e impegno da parte tua, quindi eseguire un test prima di iniziare ti consentir\u00e0 di convalidare questa idea di business online come un'idea che si ripagher\u00e0 in futuro.\n\n            03. Effettua ricerche approfondite sull'argomento\n\n            Che tu sia gi\u00e0 un esperto nel tuo campo o non veda l'ora di impararlo dall'inizio alla fine, ora \u00e8 il momento di approfondire fino a quando non saprai tutto quello che c'\u00e8 da sapere sull'argomento.\n\n            Nell'ambito del tuo approfondito processo di apprendimento, vai oltre ci\u00f2 che i partecipanti al corso troveranno facilmente nei risultati di ricerca. Fai uno sforzo in pi\u00f9 e trova una variet\u00e0 di fonti diverse sull'argomento, dalla letteratura alle lezioni dei concorrenti e ai webinar. Esegui una ricerca per parole chiave per vedere che tipo di query le persone stanno cercando sull'argomento. Da questo, puoi avere un'idea migliore del tipo di domande a cui il tuo pubblico potrebbe essere interessato.\n\n            Tieni gli occhi aperti per eventuali sottocategorie all'interno della tua nicchia. Ad esempio, se hai intenzione di tenere un corso su come prenderti cura delle piante da interno, vorrai sicuramente trattare le nozioni di base come l'acqua e la luce naturale. Ma per fornire valore aggiunto, cerca angoli unici per ampliare la portata del tuo corso, come ad esempio i tipi di impianti di purificazione dell'aria.\n\n            04. Scrivi una struttura del corso:\n\n            Ora \u00e8 il momento di sviluppare il curriculum per il tuo corso online. Su un pezzo di carta, scrivi un elenco delle diverse lezioni che intendi insegnare online. All'interno di ogni lezione, suddividila negli argomenti principali che desideri trattare. Procedi in ordine logico e cerca di far evolvere le tue idee in modo naturale dall'una all'altra, per garantire un processo di apprendimento fluido e senza attriti.\n\n            05. Creare il contenuto del corso:\n\n            Se hai gi\u00e0 esperienza professionale con l'argomento del corso, \u00e8 probabile che tu abbia messo insieme dei contenuti a riguardo in passato. Hai mai scritto un post sul blog o creato un webinar sull'argomento? Forse ospiti un podcast o gestisci un canale YouTube per la tua attivit\u00e0 in cui hai discusso temi simili? Se \u00e8 cos\u00ec, torna a questi materiali.\n\n            Riproporre i contenuti esistenti nel tuo corso online ti aiuter\u00e0 a iniziare e a risparmiare molto denaro prezioso\n\n            tempo.\n\n            06. Porta il tuo corso online:\n\n            Una volta pronti i contenuti del corso, \u00e8 il momento di creare la piattaforma per riunirli tutti. Se hai gi\u00e0 un sito web professionale, puoi aggiungere il tuo corso online come sezione l\u00ec. In caso contrario, crea un nuovo sito Web solo per questo scopo.\n\n            Se ti stai chiedendo come creare un sito web Wix,\n\n            dai un'occhiata a questi modelli di siti web di formazione online realizzati da designer per aiutarti a iniziare. Assicurati di aggiungere Wix Video al tuo sito, permettendoti di mostrare video, interagire con i visitatori e monetizzare i tuoi contenuti. Carica le tue lezioni come video indipendenti o organizzate in canali all'interno di una libreria\n\n            07. Vendi il tuo corso online\n\n            08. Commercializza i tuoi contenuti\n\n            \u00e8 ora di creare un corso online e ora \u00e8 il momento di farlo\n\n            promuoverlo e ottenere le registrazioni ai corsi. A\n\n            commercializza il tuo corso online, puoi utilizzarli entrambi gratuitamente\n\n            promozioni e tipi di marketing a pagamento. Puoi anche creare un logo per dare al tuo corso un aspetto pi\u00f9 professionale e distinguerlo mentre lo promuovi.\n\n            Negli ultimi anni ci siamo spostati per condurre molte pi\u00f9 attivit\u00e0 e apprendere online. Anche questo significa\n\n            09. Raccogli feedback:\n\n            che siamo in grado di rendere molto pi\u00f9 basati sui dati\n\n            decisioni, attingere a ricche analisi e ampliare la nostra portata\n\n            per ascoltare pi\u00f9 voci dei clienti.\n\n            Quando si tratta del tuo corso online, dovresti sfruttare le opportunit\u00e0 digitali che hai per migliorare il tuo curriculum chiedendo feedback, ad esempio durante e dopo il corso. Pi\u00f9 il tuo corso \u00e8 ottimizzato e migliorato, pi\u00f9 \u00e8 probabile che gli studenti vivano un'esperienza migliore,\n\n            consigliarti o iscriverti a futuri workshop o opportunit\u00e0 di apprendimento che potresti offrire.\n\n            Per ottenere feedback, crea sondaggi con l'aiuto di un generatore di moduli e chiedi informazioni sull'esperienza degli studenti, suggerimenti per il miglioramento e qualsiasi altra cosa sperassero di ottenere dal corso. Dopo aver misurato il successo e analizzato le risposte, puoi adattarti e continuare a correre sempre meglio\n\n            corsi."}, {"name": "Scatena la tua propriet\u00e0 online", "image": "https://raw.githubusercontent.com/E-Money-Online/E-Money-Data/main/images/pro_11.png", "description": "Se sei l'orgoglioso proprietario di una propriet\u00e0 attualmente non occupata, perch\u00e9 non metterla in affitto su siti come Airbnb? Affittare le tue propriet\u00e0 online \u00e8 un modo fantastico per assicurarti un flusso di reddito passivo mentre cerchi attivit\u00e0 alternative.\n\n            Esistono altri modi per fare soldi online con gli immobili, ecco diversi modi in cui puoi farlo\n\n            1) Prestito di denaro forte:\n\n            Il prestito di denaro forte \u00e8 una buona opzione se disponi di una grande quantit\u00e0 di capitale ma non lo desideri necessariamente\n\n            gestire un immobile\n\n            In questa situazione, l\u2019investitore guadagnerebbe un reddito agendo come prestatore e addebitando interessi mensili al mutuatario. Gli interessi sui prestiti in denaro forte sono generalmente pi\u00f9 alti della media (compresi tra il 7,5% e il 15%), ma la durata del prestito \u00e8 normalmente pi\u00f9 breve (circa 6-18 mesi)\n\n            Gli acquirenti di case tendono a cercare prestiti in denaro forte perch\u00e9 sono pi\u00f9 rapidi da ottenere rispetto a un mutuo convenzionale e hanno meno requisiti relativi alle condizioni della propriet\u00e0\n\n            2) Noleggi a lungo termine:\n\n            Diventare proprietario \u00e8 ci\u00f2 che molte persone immaginano quando pensano di investire nel settore immobiliare. Gli affitti a lungo termine vengono solitamente affittati per un anno alla volta e forniscono al proprietario un flusso costante di reddito mensile da locazione da parte degli inquilini. Essere un proprietario non \u00e8 una passeggiata nel parco, per\u00f2, e sarai responsabile delle riparazioni, della manutenzione e di eventuali problemi che si presentano con la casa.\n\n            3). Noleggi a lungo termine\n\n            Diventare un proprietario \u00e8 ci\u00f2 che molte persone immaginano\n\n            quando pensano di investire nel settore immobiliare.\n\n            Gli affitti a lungo termine vengono generalmente affittati per un anno\n\n            alla volta e fornire al proprietario una costante\n\n            flusso di reddito mensile da locazione da parte dei loro inquilini\n\n            Essere un padrone di casa, per\u00f2, non \u00e8 una passeggiata nel parco,\n\n            e sarai responsabile delle riparazioni, della manutenzione,\n\n            e tutti i problemi che sorgono con la casa. A\n\n            determinare il vero ROI di un investimento immobiliare dopo\n\n            spese, utilizzare un calcolatore di propriet\u00e0 in affitto e\n\n            fai le tue ricerche Prima di spendere migliaia di euro\n\n            ristrutturazioni e mobili costosi, sappi che il tuo\n\n            gli inquilini potrebbero non trattare la propriet\u00e0 con la stessa gentilezza di te\n\n            volevo. Piuttosto, dovresti mirare a \"a prova di inquilino\".\n\n            casa con caratteristiche come moquette resistente e\n\n            quando si verificano i danni.\n\n            4) Case vacanza:\n\n            Gli affitti per le vacanze, ovvero gli affitti a breve termine, hanno un enorme potenziale per generare flussi di cassa significativi. I proprietari possono far pagare di pi\u00f9 per notte rispetto a un affitto a lungo termine e non devono avere a che fare con inquilini difficili (almeno non per molto tempo). Inoltre, piattaforme come Vrbo e Airbnb hanno reso l\u2019affitto del tuo spazio ai vacanzieri pi\u00f9 accessibile che mai\n\n            Le case vacanze richiedono molta manutenzione e dovrai pulirle dopo ogni soggiorno, quindi tienilo a mente mentre calcoli il potenziale ROI"}, {"name": "Diventa uno streamer", "image": "https://raw.githubusercontent.com/E-Money-Online/E-Money-Data/main/images/pro_12.png", "description": "Con il decollo della scena degli eSport, molti nuovi spettatori sono stati esposti alle delizie dei videogiochi. Ci\u00f2 ha portato lo streaming di videogiochi a diventare un vero e proprio lavoro ben pagato su Internet.\n\n            Molte persone guadagnano entrate stabili giocando ai videogiochi e trasmettendoli in streaming per centinaia di persone, che spesso finiscono per fornirti anche consigli.\n\n            Ora \u00e8 il momento migliore per metterti in gioco se l\u2019idea di guadagnare un reddito giocando ti intriga anche un po\u2019.\n\n            La maggior parte degli atleti di eSport dovr\u00e0 sostenere\n\n            stessi finanziariamente attraverso lo streaming. Fornisce\n\n            loro un modo meno stressante di giocare ai videogiochi e\n\n            interagire con i propri fan.\n\n            Come posso diventare uno streamer di successo? Ci vuole impegno, la giusta attrezzatura, abilit\u00e0 nei videogiochi e una personalit\u00e0 accattivante. Lo streaming pu\u00f2 essere un ottimo modo per provvedere finanziariamente a te stesso.\n\n            Esistono alcuni siti Web diversi che attualmente dominano il mondo dello streaming di eSport. Ci concentreremo sull'utilizzo di Twitch in questo blog. Tieni presente che la maggior parte dei suggerimenti di cui discutiamo possono essere facilmente applicati a qualunque servizio di streaming tu decida di utilizzare. Speriamo che alcuni di questi consigli ti aiutino a diventare la prossima star dello streaming!"}, {"name": "Assistente virtuale", "image": "https://raw.githubusercontent.com/E-Money-Online/E-Money-Data/main/images/pro_13.png", "description": "Sei interessato a lavorare da casa e guadagnarti da vivere online? Con i progressi tecnologici che mettono il mondo a portata di mano, le aziende hanno esternalizzato molte attivit\u00e0 critiche agli assistenti virtuali.\n\n            Non devi pi\u00f9 vestirti per andare al lavoro o andare in ufficio. Ogni giorno, persone come te e me iniziano una carriera ben pagata come assistenti virtuali. Hai solo bisogno di un laptop e di Internet.\n\n            Oggi ti mostreremo come diventare un assistente virtuale e risponderemo a domande come:\n\n            1) Cosa fa un assistente virtuale? 2) Quanto puoi aspettarti di guadagnare? 3) Dove trovare lavoro come assistente virtuale?\n\n            ----Cos'\u00e8 un Assistente Virtuale?----\n\n            Gli assistenti virtuali (VA) sono professionisti indipendenti che offrono servizi come supporto amministrativo o di marketing. Ci\u00f2 che rende il lavoro attraente \u00e8 che si tratta di ruoli a distanza solitamente svolti comodamente da casa tua.\n\n            Ecco alcune responsabilit\u00e0 comuni dei VA:\n\n            Pianificazione di appuntamenti, gestione della casella di posta dei clienti, effettuazione di chiamate in entrata e in uscita e prenotazione di hotel o voli\n\n            Alcuni VA sono in grado di offrire servizi pi\u00f9 specializzati in base alle loro competenze uniche, incluso il copywriting. Sviluppo WordPress, progettazione grafica, contabilit\u00e0, contabilit\u00e0 e altri servizi di marketing.\n\n            Dal punto di vista del datore di lavoro, assistenti virtuali\n\n            offrono flessibilit\u00e0 del personale poich\u00e9 sono basati su contratti\n\n            Queste sono alcune delle principali attivit\u00e0 che puoi svolgere come assistente virtuale. Alla fine sceglierai quali servizi desideri offrire, quindi fai un brainstorming sulle tue capacit\u00e0 e interessi.\n\n            Perch\u00e9 le persone assumono assistenti virtuali?\n\n            Gli assistenti virtuali sono una parte fondamentale di molte aziende in crescita. Un motivo comune per cui i datori di lavoro assumono assistenti virtuali \u00e8 quando hanno un\u2019esigenza importante, ma non fondamentale per i loro modelli di business.\n\n            Un esempio potrebbe essere una piccola impresa che inizia a registrare una rapida crescita, ma non \u00e8 nella posizione di assumere un dipendente a tempo pieno. Potrebbero assumere un assistente virtuale per svolgere alcune delle attivit\u00e0 che richiedono pi\u00f9 tempo, come rispondere alle telefonate o alle e-mail.\n\n            Un altro esempio potrebbe essere quando un imprenditore desidera testare una nuova strategia di marketing, ma potrebbe non avere tutte le competenze per eseguirla personalmente. Potrebbero assumere un assistente virtuale che offra servizi di progettazione grafica o di gestione dei social media.\n\n            Come diventare un assistente virtuale?\n\n            Passaggio 1. Determina quali servizi desideri offrire\n\n            Passaggio 2: determina la tariffa e la struttura dei prezzi\n\n            Passaggio 3: stabilire una presenza online e generare interesse\n\n            Dove trovare lavoro come assistente virtuale?\n\n            1) Upwork e formalmente eLance/oDesk\n            2) Semplicemente assunto\n            3) TaskRabbit\n            4) Craigslist\n            5) Zirtuale\n            6) Remote.co"}, {"name": "Scaricare la consegna", "image": "https://raw.githubusercontent.com/E-Money-Online/E-Money-Data/main/images/pro_14.png", "description": "Avviare un\u2019attivit\u00e0 in dropshipping \u00e8 un ottimo primo passo verso l\u2019imprenditorialit\u00e0. Potrai vendere prodotti ai clienti, stabilire i prezzi dei prodotti e commercializzare il tuo marchio. Non \u00e8 nemmeno necessario pagare l'inventario finch\u00e9 non viene venduto a un cliente reale. Se sei disposto a inserirti\n\n            E se sei ancora indeciso se avviare un'attivit\u00e0 online, forse ti sar\u00e0 utile sapere che le vendite e-commerce ammontano a quasi 3,5 trilioni di dollari in tutto il mondo nel 2019. Quindi, se le statistiche globali sull'e-commerce sono indicative, avviare un'attivit\u00e0 online \u00e8 un'opzione sempre pi\u00f9 redditizia in questo momento\n\n            In questo articolo imparerai come avviare un dropshipping\n\n            Attivit\u00e0 commerciale. Spiegheremo cos'\u00e8 un dropshipping\n\n            il business \u00e8 come trovare il dropshipping giusto\n\n            idee imprenditoriali e tutto ci\u00f2 di cui hai bisogno\n\n            sapere per iniziare il dropshipping\n\n            1) Che cos'\u00e8 un'attivit\u00e0 di dropshipping?\n\n            Il dropshipping \u00e8 un modello di business che puoi utilizzare per gestire il tuo negozio senza mai tenere alcun inventario. Una volta effettuata una vendita, il tuo fornitore spedir\u00e0 i tuoi prodotti dal suo magazzino, direttamente a casa del tuo cliente. Non dovrai mai preoccuparti di conservare, imballare o spedire i tuoi prodotti\n\n            2) Come funziona il modello di business del dropshipping?\n\n            Ci sono tre attori chiave nel modello di business dropshipping: il produttore, il rivenditore (tu) e il cliente\n\n            Il ruolo del produttore in un modello di business dropshipping include la creazione di prodotti, il trasporto dell'inventario, la spedizione dei prodotti ai clienti per conto del rivenditore, la sostituzione dei prodotti difettosi e il loro riassortimento. Vendono prodotti al rivenditore a prezzi all'ingrosso assumendosi il rischio di inventario invenduto\n\n            Nel modello di business dropshipping, il rivenditore (tu), vende i prodotti sul tuo sito web con il tuo marchio. Sarai responsabile della scelta e della commercializzazione di tali prodotti. Inoltre, sarai anche responsabile dei costi di spedizione e della definizione dei prezzi che ti consentiranno di ottenere un profitto.\n\n            Infine, nel modello di business dropshipping, il cliente acquista i prodotti direttamente da te, il rivenditore. Se sorgono domande o problemi, contattano il rivenditore da cui hanno acquistato il prodotto\n\n            3) Quanto \u00e8 redditizio il Dropshipping?\n\n            Questa \u00e8 una domanda frequente sul dropshipping che sentiamo abbastanza spesso. Il dropshipping pu\u00f2 essere il modello di business pi\u00f9 redditizio di tutti, poich\u00e9 non sei responsabile dei costi di spedizione e produzione. Per questo motivo \u00e8 possibile ottenere rapidamente profitti una volta trovati i fornitori giusti con Oberlo.\n\n            4) Puoi guadagnare denaro con il dropshipping?\n\n            S\u00ec, puoi guadagnare denaro tramite dropshipping. come continuano a fare molti dei nostri commercianti di successo. Il dropshipping ti consente di trovare prodotti con un enorme potenziale di profitto e di avviare un'attivit\u00e0 vendendoli. Quando sei motivato a vendere prodotti, \u00e8 pi\u00f9 probabile che investi pi\u00f9 tempo nella promozione e nel marketing, ottenendo maggiori profitti dai tuoi sforzi."}, {"name": "Diventa un copywriter", "image": "https://raw.githubusercontent.com/E-Money-Online/E-Money-Data/main/images/pro_15.png", "description": "In questo mondo di e-mail e messaggi sui social media, un testo convincente \u00e8 ormai una priorit\u00e0. Creare annunci per aziende o scrivere contenuti informativi pu\u00f2 aiutarti a guadagnare denaro extra ogni mese.\n\n            Come libero professionista, ci sono molte opportunit\u00e0 di scrivere per pubblicazioni puramente digitali - senza costi di stampa da considerare - quindi non aver paura di iniziare in piccolo.\n\n            Se non ti piace l'idea di affrontare il mondo del copywriting da solo, ci sono diversi siti come Elance o Freelancer che possono aiutarti a trovare opportunit\u00e0 di scrittura."}, {"name": "Grafico", "image": "https://raw.githubusercontent.com/E-Money-Online/E-Money-Data/main/images/pro_16.png", "description": "Diventare un grafico pu\u00f2 infatti essere un valido modo per fare soldi online. Ecco alcuni passaggi che puoi eseguire per iniziare:\n\n            1. Sviluppa le tue capacit\u00e0: inizia imparando i fondamenti della progettazione grafica. Acquisisci familiarit\u00e0 con i principi di progettazione, la teoria dei colori, la tipografia e i software di progettazione pi\u00f9 diffusi come Adobe\n\n            Certamente! Come grafico, ci sono diversi modi per guadagnare soldi online. Ecco alcune strade che puoi esplorare:\n\n            1. Piattaforme freelance: iscriviti su siti Web freelance come Upwork, Fiverr o Freelancer. Crea un profilo che evidenzi le tue competenze e il tuo portfolio e fai offerte per progetti di progettazione grafica pertinenti pubblicati dai clienti. Completa gli incarichi e costruisci una solida reputazione per attirare pi\u00f9 clienti.\n\n            2. Mercati online: valuta la possibilit\u00e0 di vendere i tuoi servizi di progettazione grafica su mercati online come Etsy o Creative Market. Crea prodotti digitali come modelli, loghi, icone o grafica per social media e offrili in vendita. \u00c8 inoltre possibile offrire servizi di personalizzazione per soddisfare le esigenze specifiche del cliente.\n\n            3. Crea un sito Web portfolio: sviluppa un sito Web professionale che mostri i tuoi lavori migliori. Includere"}, {"name": "Rappresentante del Servizio Clienti", "image": "https://raw.githubusercontent.com/E-Money-Online/E-Money-Data/main/images/pro_17.png", "description": "Certamente! Ecco un esempio di contenuto che mostra come un rappresentante del servizio clienti pu\u00f2 aiutare le aziende online:\nTitolo: Migliora la soddisfazione dei clienti e potenzia il tuo business online con il supporto del servizio clienti professionale\n\n1. Comunicazione tempestiva e reattiva:\nI nostri rappresentanti del servizio clienti sono disponibili tramite vari canali come chat dal vivo, e-mail e telefono, garantendo che le richieste e le preoccupazioni dei tuoi clienti vengano affrontate in modo tempestivo. Diamo priorit\u00e0 a risposte tempestive per migliorare la soddisfazione del cliente e ridurre i tempi di risposta.\n\n2. Assistenza e tracciamento degli ordini:\n Il nostro team eccelle nel fornire un supporto completo durante tutto il processo di ordine. Assistiamo i clienti nell'effettuare ordini, rispondere a domande relative ai prodotti e fornire aggiornamenti sullo stato dell'ordine e sul monitoraggio della spedizione. Offrendo un'assistenza continua, aiutiamo a semplificare l'esperienza di acquisto e a promuovere la fiducia nel tuo marchio.\n\n3. Risoluzione dei problemi e supporto tecnico: i nostri rappresentanti qualificati sono esperti nella gestione di domande tecniche e nella risoluzione di problemi comuni. Che si tratti della navigazione nel tuo sito web, della risoluzione di problemi relativi al prodotto o dell'assistenza in caso di problemi software, forniamo una guida esperta per garantire interazioni fluide e un'esperienza cliente positiva.\n\n4. Feedback dei clienti e risoluzione dei problemi:\n Comprendiamo l'importanza del feedback e della risoluzione dei clienti"}, {"name": "Agente di viaggi", "image": "https://raw.githubusercontent.com/E-Money-Online/E-Money-Data/main/images/pro_18.png", "description": "Se vuoi diventare un agente di viaggio e guadagnare soldi online, ecco alcuni passaggi che possono aiutarti:\n\n            1. Definisci la tua specializzazione: decidi in anticipo che tipo di agente di viaggio vuoi essere. Alcuni si concentrano su pacchetti turistici nazionali o internazionali, mentre altri sono specializzati in viaggi avventurosi o di lusso. Determina i tuoi interessi e i tuoi punti di forza per definire la tua specializzazione.\n\n            2. Acquisire conoscenze: \u00e8 importante rimanere aggiornati sul settore dei viaggi. Raccogli maggiori informazioni sulle tue destinazioni preferite, sui pacchetti di viaggio, sui processi di rilascio di visti e passaporti e sui servizi di viaggio disponibili. Utilizza siti Web, blog e libri affidabili come risorse.\n\n            3. Costruire relazioni: costruire"}]